bugpy/__init__.py
bugpy/db_manager.py
bugpy/data/__init__.py
bugpy/data/download_blobs.py
bugpy/data/move_blobs.py
bugpy/data/tools.py
bugpy/data/upload_blobs.py
bugpy/ingestion/__init__.py
bugpy/ingestion/collect_metadata.py
bugpy/ingestion/upload_insert.py
bugpy/process/__init__.py
bugpy/process/process_data.py
bugpy/utils/__init__.py
bugpy/utils/sqlformatter.py
bugpy/utils/tools.py
bugpy-0.0.79.dist-info/licenses/LICENSE
bugpy-0.0.79.dist-info/METADATA
bugpy-0.0.79.dist-info/WHEEL
bugpy-0.0.79.dist-info/top_level.txt
bugpy-0.0.79.dist-info/RECORD
