Metadata-Version: 2.4
Name: bugpy
Version: 0.0.79
Summary: Internal package for BickLab data management and analysis
Author-email: Laurence Still <lstill2@wisc.edu>
License: Copyright (c) 2018 The Python Packaging Authority
Project-URL: Homepage, https://git.doit.wisc.edu/insecteavesdropper/data-management/bugpy
Project-URL: Issues, https://git.doit.wisc.edu/insecteavesdropper/data-management/bugpy/issues
Classifier: Programming Language :: Python :: 3
Classifier: License :: OSI Approved :: MIT License
Classifier: Operating System :: OS Independent
Requires-Python: >=3.8
License-File: LICENSE
Requires-Dist: pandas>=1.0.0
Requires-Dist: mysql-connector-python>=9.0.0
Requires-Dist: setuptools>=65.5.1
Requires-Dist: numpy>=1.19.5
Requires-Dist: openpyxl>=3.1.5
Requires-Dist: tqdm>=4.66.4
Requires-Dist: toml>=0.10.2
Requires-Dist: boto3>=1.35.0
Requires-Dist: keyring>=25.2.1
Requires-Dist: keyrings.alt>=5.0.2
Requires-Dist: sphinx>=7.0.0
Requires-Dist: librosa>=0.10.2.post1
Requires-Dist: numexpr>=2.8.4
Requires-Dist: bottleneck>=1.3.6
Dynamic: license-file
